CanbusHandler/__init__.py
CanbusHandler/canbus_handler.py
CanbusHandler-0.2.dist-info/METADATA
CanbusHandler-0.2.dist-info/WHEEL
CanbusHandler-0.2.dist-info/top_level.txt
CanbusHandler-0.2.dist-info/RECORD
